cw/__init__.py
cw/resolution.py
cw/scrap.py
cw/util.py
cw-0.0.13.dist-info/licenses/LICENSE
cw-0.0.13.dist-info/METADATA
cw-0.0.13.dist-info/WHEEL
cw-0.0.13.dist-info/top_level.txt
cw-0.0.13.dist-info/RECORD
