Metadata-Version: 2.4
Name: cw
Version: 0.0.13
Summary: Command line Wizard - Transform your python functions into CLI tools
Home-page: https://github.com/i2mint/cw
License: mit
Platform: any
License-File: LICENSE
Requires-Dist: i2
Requires-Dist: argh
Dynamic: license-file
